spiceitup/__init__.py
spiceitup/__main__.py
spiceitup/debug.log
spiceitup/pres_notes.txt
spiceitup/run.py
spiceitup/__pycache__/__main__.cpython-313.pyc
spiceitup/__pycache__/run.cpython-313.pyc
spiceitup/docs/Qt_cursors.png
spiceitup/docs/__init__.py
spiceitup/docs/code_conventions.txt
spiceitup/docs/layout.drawio
spiceitup/docs/layout.png
spiceitup/docs/menu_layout.ods
spiceitup/docs/plots_layout.ods
spiceitup/docs/windows_installation.pdf
spiceitup/docs/codimd_backup/2023_06_13.md
spiceitup/docs/codimd_backup/2023_07_07.md
spiceitup/docs/codimd_backup/2023_09_26.md
spiceitup/docs/codimd_backup/2023_11_28.md
spiceitup/docs/codimd_backup/2024_06_26.md
spiceitup/docs/codimd_backup/2024_07_12.md
spiceitup/docs/codimd_backup/2024_08_29_TBC.md
spiceitup/docs/microsoft365_backup/SPICE_Quicklook_Tasks_20240912.xlsx
spiceitup/docs/microsoft365_backup/SPICE_Quicklook_Tasks_20241002.xlsx
spiceitup/docs/microsoft365_backup/SPICE_Quicklook_Tasks_20241007.xlsx
spiceitup/docs/microsoft365_backup/SPICE_Quicklook_Tasks_20241021.xlsx
spiceitup/docs/microsoft365_backup/SPICE_Quicklook_Tasks_20241102.xlsx
spiceitup/docs/microsoft365_backup/SPICE_Quicklook_Tasks_20241118.xlsx
spiceitup/docs/microsoft365_backup/SPICE_Quicklook_Tasks_20241129.xlsx
spiceitup/docs/microsoft365_backup/SPICE_Quicklook_Tasks_20241209.xlsx
spiceitup/docs/microsoft365_backup/SPICE_Quicklook_Tasks_20250120.xlsx
spiceitup/docs/microsoft365_backup/SPICE_Quicklook_Tasks_20250123.xlsx
spiceitup/docs/microsoft365_backup/SPICE_Quicklook_Tasks_20250217.xlsx
spiceitup/docs/user_manual/fit_maps.png
spiceitup/docs/user_manual/several_x_y.png
spiceitup/docs/user_manual/user_documentation.docx
spiceitup/docs/user_manual/user_documentation.pdf
spiceitup/docs/user_manual/user_manual.pptx
spiceitup/docs/user_manual/~$er_documentation.docx
spiceitup/docs/user_manual/screenshot_2025/1.png
spiceitup/docs/user_manual/screenshot_2025/2.png
spiceitup/docs/user_manual/screenshot_2025/3.png
spiceitup-1.3.4.dist-info/METADATA
spiceitup-1.3.4.dist-info/WHEEL
spiceitup-1.3.4.dist-info/entry_points.txt
spiceitup-1.3.4.dist-info/top_level.txt
spiceitup-1.3.4.dist-info/RECORD
