Metadata-Version: 2.4
Name: spiceitup
Version: 1.3.4
Summary: Quicklook tool for level 2 SPICE imaging
Home-page: https://git.ias.u-psud.fr/spice/data_quicklook
Author: David Picard
Author-email: david.picard@universite-paris-saclay.fr
Classifier: Programming Language :: Python :: 3
Classifier: License :: OSI Approved :: MIT License
Requires-Python: >=3.7
Requires-Dist: PyQt5
Requires-Dist: sunraster
Requires-Dist: pyqtgraph
Requires-Dist: qdarkgraystyle
Requires-Dist: scipy
Requires-Dist: opencv-python-headless
Dynamic: author
Dynamic: author-email
Dynamic: classifier
Dynamic: description
Dynamic: description-content-type
Dynamic: home-page
Dynamic: requires-dist
Dynamic: requires-python
Dynamic: summary
